justlucifer123456/__init__.py
justlucifer123456/pp.py
storeadddddddasdfads/__init__.py
storeadddddddasdfads/pp.py
jjjjlucifer123-12.0.9.dist-info/LICENSE
jjjjlucifer123-12.0.9.dist-info/METADATA
jjjjlucifer123-12.0.9.dist-info/WHEEL
jjjjlucifer123-12.0.9.dist-info/top_level.txt
jjjjlucifer123-12.0.9.dist-info/RECORD
